ecape_parcel/__about__.py
ecape_parcel/__init__.py
ecape_parcel/calc.py
ecape_parcel/ecape_calc.py
ecape_parcel-1.2.2.dist-info/METADATA
ecape_parcel-1.2.2.dist-info/WHEEL
ecape_parcel-1.2.2.dist-info/licenses/LICENSE
ecape_parcel-1.2.2.dist-info/RECORD
