Metadata-Version: 2.1
Name: ecape-parcel
Version: 1.2.2
Summary: A simple Python package that computes entrainment CAPE parcels.
Project-URL: Documentation, https://github.com/a-urq/ecape-parcel-py#readme
Project-URL: Issues, https://github.com/a-urq/ecape-parcel-py/issues
Project-URL: Source, https://github.com/a-urq/ecape-parcel-py
Author-email: a-urq <amelia.r.urquhart@gmail.com>
License-Expression: MIT
License-File: LICENSE
Classifier: Development Status :: 4 - Beta
Classifier: Programming Language :: Python
Classifier: Programming Language :: Python :: 3.8
Classifier: Programming Language :: Python :: 3.9
Classifier: Programming Language :: Python :: 3.10
Classifier: Programming Language :: Python :: 3.11
Classifier: Programming Language :: Python :: 3.12
Classifier: Programming Language :: Python :: Implementation :: CPython
Classifier: Programming Language :: Python :: Implementation :: PyPy
Requires-Python: >=3.8
Requires-Dist: ecape
Requires-Dist: metpy
